{"name":"ingreso a maxtime y se realiza el reporte del dia","id":"hacer-el-maxtime-de-manera-automatizada;ingreso-a-maxtime-y-se-realiza-el-reporte-del-dia","testSteps":[{"number":1,"description":"Given ingreso a MaxTime","duration":17860,"startTime":"2019-10-08T15:24:55.316-05:00[America/Bogota]","screenshots":[{"screenshot":"3f1b924cf7d33e3cfdb32434c68d46f5a58b6dffbbd9b41a1700fd7a0a351525.png","timeStamp":1570566313176}],"result":"SUCCESS","precondition":false,"level":0,"children":[{"number":2,"description":"Entrar maxtime","duration":17242,"startTime":"2019-10-08T15:24:55.929-05:00[America/Bogota]","screenshots":[{"screenshot":"3f1b924cf7d33e3cfdb32434c68d46f5a58b6dffbbd9b41a1700fd7a0a351525.png","timeStamp":1570566313170}],"result":"SUCCESS","precondition":false,"level":1}]},{"number":3,"description":"When realizo el reporte del dia","duration":17118,"startTime":"2019-10-08T15:25:13.177-05:00[America/Bogota]","exception":{"errorType":"org.openqa.selenium.interactions.MoveTargetOutOfBoundsException","message":"move target out of bounds\n  (Session info: chrome\u003d77.0.3865.90)\nBuild info: version: \u00273.141.59\u0027, revision: \u0027e82be7d358\u0027, time: \u00272018-11-14T08:17:03\u0027\nSystem info: host: \u0027CHMEPPF0HDQQD\u0027, ip: \u0027172.17.27.126\u0027, os.name: \u0027Windows 10\u0027, os.arch: \u0027amd64\u0027, os.version: \u002710.0\u0027, java.version: \u00271.8.0_211\u0027\nDriver info: org.openqa.selenium.remote.RemoteWebDriver\nCapabilities {acceptInsecureCerts: false, browserName: chrome, browserVersion: 77.0.3865.90, chrome: {chromedriverVersion: 77.0.3865.40 (f484704e052e0..., userDataDir: C:\\Users\\cmestral\\AppData\\L...}, goog:chromeOptions: {debuggerAddress: localhost:51653}, javascriptEnabled: true, networkConnectionEnabled: false, pageLoadStrategy: normal, platform: XP, platformName: XP, proxy: Proxy(), setWindowRect: true, strictFileInteractability: false, timeouts: {implicit: 0, pageLoad: 300000, script: 30000}, unhandledPromptBehavior: dismiss and notify}\nSession ID: d660293f0c69b007629c5d0132a47339\nBuild info: version: \u00273.141.59\u0027, revision: \u0027e82be7d358\u0027, time: \u00272018-11-14T08:17:03\u0027\nSystem info: host: \u0027CHMEPPF0HDQQD\u0027, ip: \u0027172.17.27.126\u0027, os.name: \u0027Windows 10\u0027, os.arch: \u0027amd64\u0027, os.version: \u002710.0\u0027, java.version: \u00271.8.0_211\u0027\nDriver info: driver.version: unknown","stackTrace":[{"declaringClass":"com.choucair.formacion.pageobjects.maxTimePage","methodName":"realizarNuevoReporte","fileName":"maxTimePage.java","lineNumber":45},{"declaringClass":"com.choucair.formacion.steps.maxTimeSteps","methodName":"realizarReporte","fileName":"maxTimeSteps.java","lineNumber":17},{"declaringClass":"com.choucair.formacion.definition.maxTimeDefinitions","methodName":"realizo_el_reporte_del_dia","fileName":"maxTimeDefinitions.java","lineNumber":21},{"declaringClass":"✽","methodName":"realizo el reporte del dia","fileName":"src/test/resources/features/maxTime.feature","lineNumber":5}]},"result":"ERROR","precondition":false,"level":0,"children":[{"number":4,"description":"Realizar reporte","duration":376,"startTime":"2019-10-08T15:25:29.909-05:00[America/Bogota]","screenshots":[{"screenshot":"ab4db59714fd90c3252bcaafeebea57d8151dfd2b868ee18d84cbd7727d1f765.png","htmlSource":"pagesource2945897049643525112.html.txt","timeStamp":1570566330272}],"exception":{"errorType":"org.openqa.selenium.interactions.MoveTargetOutOfBoundsException","message":"move target out of bounds\n  (Session info: chrome\u003d77.0.3865.90)\nBuild info: version: \u00273.141.59\u0027, revision: \u0027e82be7d358\u0027, time: \u00272018-11-14T08:17:03\u0027\nSystem info: host: \u0027CHMEPPF0HDQQD\u0027, ip: \u0027172.17.27.126\u0027, os.name: \u0027Windows 10\u0027, os.arch: \u0027amd64\u0027, os.version: \u002710.0\u0027, java.version: \u00271.8.0_211\u0027\nDriver info: org.openqa.selenium.remote.RemoteWebDriver\nCapabilities {acceptInsecureCerts: false, browserName: chrome, browserVersion: 77.0.3865.90, chrome: {chromedriverVersion: 77.0.3865.40 (f484704e052e0..., userDataDir: C:\\Users\\cmestral\\AppData\\L...}, goog:chromeOptions: {debuggerAddress: localhost:51653}, javascriptEnabled: true, networkConnectionEnabled: false, pageLoadStrategy: normal, platform: XP, platformName: XP, proxy: Proxy(), setWindowRect: true, strictFileInteractability: false, timeouts: {implicit: 0, pageLoad: 300000, script: 30000}, unhandledPromptBehavior: dismiss and notify}\nSession ID: d660293f0c69b007629c5d0132a47339","stackTrace":[{"declaringClass":"com.choucair.formacion.pageobjects.maxTimePage","methodName":"realizarNuevoReporte","fileName":"maxTimePage.java","lineNumber":45},{"declaringClass":"com.choucair.formacion.steps.maxTimeSteps","methodName":"realizarReporte","fileName":"maxTimeSteps.java","lineNumber":17},{"declaringClass":"com.choucair.formacion.definition.maxTimeDefinitions","methodName":"realizo_el_reporte_del_dia","fileName":"maxTimeDefinitions.java","lineNumber":21},{"declaringClass":"cucumber.runner.Runner","methodName":"runPickle","fileName":"Runner.java","lineNumber":80}]},"result":"ERROR","precondition":false,"level":1}]},{"number":5,"description":"Then verifico el cierre del dia de manera correcta","duration":2,"startTime":"2019-10-08T15:25:30.295-05:00[America/Bogota]","result":"SKIPPED","precondition":false,"level":0}],"userStory":{"id":"hacer-el-maxtime-de-manera-automatizada","storyName":"Hacer el maxTime de manera automatizada","path":"src/test/resources/features/maxTime.feature","type":"feature"},"featureTag":{"name":"Features/Hacer el maxTime de manera automatizada","type":"feature"},"title":"ingreso a maxtime y se realiza el reporte del dia","tags":[{"name":"Max","type":"tag"},{"name":"Hacer el maxTime de manera automatizada","type":"feature"}],"startTime":"2019-10-08T15:24:54.928-05:00[America/Bogota]","duration":35370,"testFailureCause":{"errorType":"org.openqa.selenium.interactions.MoveTargetOutOfBoundsException","message":"move target out of bounds\n  (Session info: chrome\u003d77.0.3865.90)\nBuild info: version: \u00273.141.59\u0027, revision: \u0027e82be7d358\u0027, time: \u00272018-11-14T08:17:03\u0027\nSystem info: host: \u0027CHMEPPF0HDQQD\u0027, ip: \u0027172.17.27.126\u0027, os.name: \u0027Windows 10\u0027, os.arch: \u0027amd64\u0027, os.version: \u002710.0\u0027, java.version: \u00271.8.0_211\u0027\nDriver info: org.openqa.selenium.remote.RemoteWebDriver\nCapabilities {acceptInsecureCerts: false, browserName: chrome, browserVersion: 77.0.3865.90, chrome: {chromedriverVersion: 77.0.3865.40 (f484704e052e0..., userDataDir: C:\\Users\\cmestral\\AppData\\L...}, goog:chromeOptions: {debuggerAddress: localhost:51653}, javascriptEnabled: true, networkConnectionEnabled: false, pageLoadStrategy: normal, platform: XP, platformName: XP, proxy: Proxy(), setWindowRect: true, strictFileInteractability: false, timeouts: {implicit: 0, pageLoad: 300000, script: 30000}, unhandledPromptBehavior: dismiss and notify}\nSession ID: d660293f0c69b007629c5d0132a47339","stackTrace":[{"declaringClass":"com.choucair.formacion.pageobjects.maxTimePage","methodName":"realizarNuevoReporte","fileName":"maxTimePage.java","lineNumber":45},{"declaringClass":"com.choucair.formacion.steps.maxTimeSteps","methodName":"realizarReporte","fileName":"maxTimeSteps.java","lineNumber":17},{"declaringClass":"com.choucair.formacion.definition.maxTimeDefinitions","methodName":"realizo_el_reporte_del_dia","fileName":"maxTimeDefinitions.java","lineNumber":21},{"declaringClass":"cucumber.runner.Runner","methodName":"runPickle","fileName":"Runner.java","lineNumber":80}]},"testFailureClassname":"org.openqa.selenium.interactions.MoveTargetOutOfBoundsException","testFailureMessage":"move target out of bounds\n  (Session info: chrome\u003d77.0.3865.90)\nBuild info: version: \u00273.141.59\u0027, revision: \u0027e82be7d358\u0027, time: \u00272018-11-14T08:17:03\u0027\nSystem info: host: \u0027CHMEPPF0HDQQD\u0027, ip: \u0027172.17.27.126\u0027, os.name: \u0027Windows 10\u0027, os.arch: \u0027amd64\u0027, os.version: \u002710.0\u0027, java.version: \u00271.8.0_211\u0027\nDriver info: org.openqa.selenium.remote.RemoteWebDriver\nCapabilities {acceptInsecureCerts: false, browserName: chrome, browserVersion: 77.0.3865.90, chrome: {chromedriverVersion: 77.0.3865.40 (f484704e052e0..., userDataDir: C:\\Users\\cmestral\\AppData\\L...}, goog:chromeOptions: {debuggerAddress: localhost:51653}, javascriptEnabled: true, networkConnectionEnabled: false, pageLoadStrategy: normal, platform: XP, platformName: XP, proxy: Proxy(), setWindowRect: true, strictFileInteractability: false, timeouts: {implicit: 0, pageLoad: 300000, script: 30000}, unhandledPromptBehavior: dismiss and notify}\nSession ID: d660293f0c69b007629c5d0132a47339","testFailureSummary":"ERROR;org.openqa.selenium.interactions.MoveTargetOutOfBoundsException;move target out of bounds\n  (Session info: chrome\u003d77.0.3865.90)\nBuild info: version: \u00273.141.59\u0027, revision: \u0027e82be7d358\u0027, time: \u00272018-11-14T08:17:03\u0027\nSystem info: host: \u0027CHMEPPF0HDQQD\u0027, ip: \u0027172.17.27.126\u0027, os.name: \u0027Windows 10\u0027, os.arch: \u0027amd64\u0027, os.version: \u002710.0\u0027, java.version: \u00271.8.0_211\u0027\nDriver info: org.openqa.selenium.remote.RemoteWebDriver\nCapabilities {acceptInsecureCerts: false, browserName: chrome, browserVersion: 77.0.3865.90, chrome: {chromedriverVersion: 77.0.3865.40 (f484704e052e0..., userDataDir: C:\\Users\\cmestral\\AppData\\L...}, goog:chromeOptions: {debuggerAddress: localhost:51653}, javascriptEnabled: true, networkConnectionEnabled: false, pageLoadStrategy: normal, platform: XP, platformName: XP, proxy: Proxy(), setWindowRect: true, strictFileInteractability: false, timeouts: {implicit: 0, pageLoad: 300000, script: 30000}, unhandledPromptBehavior: dismiss and notify}\nSession ID: d660293f0c69b007629c5d0132a47339;maxTimePage.java","projectKey":"","annotatedResult":"ERROR","sessionId":"d660293f0c69b007629c5d0132a47339","driver":"chrome","manual":false,"testSource":"Cucumber","result":"ERROR"}